unofficialmailpoof/__init__.py
unofficialmailpoof-0.0.9.dist-info/LICENSE
unofficialmailpoof-0.0.9.dist-info/METADATA
unofficialmailpoof-0.0.9.dist-info/WHEEL
unofficialmailpoof-0.0.9.dist-info/top_level.txt
unofficialmailpoof-0.0.9.dist-info/RECORD
